<exclusions>
    <exclusion pattern="javax/swing/event.*"/>
    <exclusion pattern="javax/swing/text.*"/>
    <exclusion pattern="javax/swing/table.*"/>
    <exclusion pattern="javax/swing/undo.*"/>
    <exclusion pattern="javax/swing/plaf.*"/>
    <exclusion pattern="javax/swing/tree.*"/>
    <exclusion pattern="javax/swing/DefaultListModel.*"/>
    <exclusion pattern="org/jdom2/.*"/>
    <exclusion pattern="java/util/[^S].*"/>
    <exclusion pattern="java/nio/.*"/>
    <exclusion pattern="java/io/.*"/>
    <exclusion pattern="java/net/.*"/>
    <exclusion pattern="sun/reflect/.*"/>
    <exclusion pattern="java/lang/AbstractStringBuilder.*"/>
    <!--<exclusion pattern="java/lang/StringBuffer.*"/>-->
    <exclusion pattern="java/lang/AssertionError.*"/>
    <exclusion pattern="java/lang/CharacterData.*"/>
    <exclusion pattern="java/lang/Integer.*"/>
    <exclusion pattern="sun/awt/.*"/>
    <exclusion pattern="sun/swing/.*"/>
    <exclusion pattern="com/sun/.*"/>
    <exclusion pattern="sun/.*"/>
    <exclusion pattern="apple/awt/.*"/>
    <exclusion pattern="com/apple/.*"/>
    <exclusion pattern="com/sun/syndication/.*"/>
    <exclusion pattern="org/eclipse/jetty/util/StringUtil.*"/>
    <exclusion pattern="org/eclipse/jetty/http/HttpFields.*"/>
    <exclusion pattern="org/eclipse/jetty/util/log/.*"/>
    <exclusion pattern="org/eclipse/jetty/util/Utf8StringBuilder.*"/>
    <exclusion pattern="org/eclipse/jetty/util/UrlEncoded.*"/>
    <exclusion pattern="org/eclipse/jetty/util/TypeUtil.*"/>
    <exclusion pattern="org/eclipse/jetty/util/StringMap.*"/>
    <exclusion pattern="org/eclipse/jetty/util/LazyList.*"/>
    <exclusion pattern="org/eclipse/jetty/io/BufferCache.*"/>
    <exclusion pattern="org/owasp/webgoat/session/DatabaseUtilities*"/>
    <exclusion pattern="org/eclipse/jetty/http/MimeTypes.*"/>
    <exclusion pattern="org/apache/ecs/.*"/>
    <exclusion pattern="PubSubHubbub/Web.*"/>
    <exclusion pattern="java/security/"/>
    <exclusion pattern="java/lang/reflect.*"/>
    <exclusion pattern="java/lang/String/char*"/>
    <exclusion pattern="java/lang/Class/checkInitted.*"/>
    <exclusion pattern="java/lang/Class/getDeclaredMethods0.*"/>
    <exclusion pattern="java/lang/Class/privateGetDeclaredMethods.*"/>
    <exclusion pattern="java/lang/SecurityManager.*"/>
    <exclusion pattern="java/lang/ref.*"/>
    <exclusion pattern="java/lang/Integer.*"/>
    <exclusion pattern="java/lang/Class/getMethod0.*"/>
    <exclusion pattern="net/sf/regain/RegainToolkit"/>
    <exclusion pattern="net/sf/regain/RegainToolkit"/>
    <exclusion pattern="net/sf/regain/search/IndexSearcherManager.*"/>
    <exclusion pattern="PubSubHubbub/Web.*"/>
    <exclusion pattern="com/sun/syndication/io.*"/>
    <exclusion pattern="pt/uc/dei/wsvdbench/util.*"/>
    <exclusion pattern="org/owasp/webgoat/util.*"/>
    <exclusion pattern="java/text.*"/>
    <exclusion pattern="org/apache/roller/weblogger/util.*"/>
    <exclusion pattern="org/apache/commons.*"/>
    <exclusion pattern="org/apache/roller/weblogger/config.*"/>
    <exclusion pattern="org/apache/roller/weblogger/ui/core/RollerSession.*"/>
    <exclusion pattern="org/kamranzafar/auth/rs/Configuration.*"/>
    <exclusion pattern="org/kamranzafar/auth/rs/ldap/LdapConfig.*"/>
    <exclusion pattern="org/kamranzafar/auth/rs/AuthResponse.*"/>
    <exclusion pattern="javax/naming.*"/>
    <exclusion pattern="org/kamranzafar/auth/rs/ldap/LdapAuthentication.*"/>
    <exclusion pattern="org/kamranzafar/auth/rs/AuthException.*"/>
    <exclusion pattern="org/kamranzafar/auth/rs/StringUtils.*"/>
    <exclusion pattern="net/sf/regain/util/io/HtmlEntities.*"/>
    <exclusion pattern="org/apache/lucene.*"/>

    <exclusion pattern="net/sf/regain/search/config.*"/>
    <exclusion pattern="org/apache/commons/httpclient.*"/>
    <exclusion pattern="net/sourceforge/pebble/web/view.*"/>
    <exclusion pattern="net/sourceforge/pebble/web/validation.*"/>
    <exclusion pattern="java/util.*"/>
    <exclusion pattern="java/io.*"/>
    <exclusion pattern="java/text.*"/>
    <exclusion pattern="java/beans.*"/>
    <exclusion pattern="org/apache/commons.*"/>

    <!--<exclusion pattern="net/sourceforge/pebble/util/CookieUtils.*"/>
    <exclusion pattern="net/sourceforge/pebble/util/ExceptionUtils.*"/>
    <exclusion pattern="net/sourceforge/pebble/util/FileUtils.*"/>
    <exclusion pattern="net/sourceforge/pebble/util/HttpURLRewriter.*"/>
    <exclusion pattern="net/sourceforge/pebble/util/I18n.*"/>
    <exclusion pattern="net/sourceforge/pebble/util/MailUtils.*"/>
    <exclusion pattern="net/sourceforge/pebble/util/NullUrlRewriter.*"/>
    <exclusion pattern="net/sourceforge/pebble/util/Pageable.*"/>
    <exclusion pattern="net/sourceforge/pebble/util/RelativeDate.*"/>
    <exclusion pattern="net/sourceforge/pebble/util/SecurityUtils.*"/>
    <exclusion pattern="net/sourceforge/pebble/util/UpgradeUtilities.*"/>
    <exclusion pattern="net/sourceforge/pebble/util/Utilities.*"/>-->
    <!--<exclusion pattern="javax/swing/.*"/>
<exclusion pattern="java/awt/.*"/>-->

    <!--<exclusion pattern="org/eclipse/jetty/util/component/.*"/>
<exclusion pattern="java/lang/Throwable.*"/>
-->
    <!--<exclusion pattern="net/sf/regain/util.*"/>-->
</exclusions>
